Metadata-Version: 2.1
Name: example_package_lhc
Version: 0.0.2
Summary: extension tools of finlab
Author-email: Hung-Ching-Lee <f128930847@gmail.com>
Project-URL: Homepage, https://github.com/Hung-Ching-Lee/finlab_exten?tab=readme-ov-file
Project-URL: Issues, https://github.com/pypa/sampleproject/issues
Classifier: Programming Language :: Python :: 3
Classifier: License :: OSI Approved :: MIT License
Classifier: Operating System :: OS Independent
Requires-Python: >=3.10
License-File: LICENSE
